notify/__init__.py
notify/channels/__init__.py
notify/channels/bark.py
notify/channels/base.py
notify/channels/chanify.py
notify/channels/ding.py
notify/channels/email.py
notify/channels/pushdeer.py
notify/channels/pushover.py
notify/channels/wechat.py
notify/notification.py
ml_simple_notify-0.2.1.dist-info/METADATA
ml_simple_notify-0.2.1.dist-info/WHEEL
ml_simple_notify-0.2.1.dist-info/RECORD
